titifel_pyip/__init__.py
titifel_pyip-7.0.0.dist-info/METADATA
titifel_pyip-7.0.0.dist-info/WHEEL
titifel_pyip-7.0.0.dist-info/top_level.txt
titifel_pyip-7.0.0.dist-info/RECORD
