Metadata-Version: 2.4
Name: titifel-pyip
Version: 7.0.0
Summary: Dependency confusion PoC package
Author: Your Name
Author-email: you@example.com
Requires-Python: >=3.6
Dynamic: author
Dynamic: author-email
Dynamic: requires-python
Dynamic: summary
